{"cameraMode":{"drawMode":0,"name":"Shaded","section":"Shading Mode"},"sceneLighting":false,"audioPlay":false,"sceneViewState":{"showFog":true,"showMaterialUpdate":false,"showSkybox":false,"showFlares":true,"showImageEffects":true,"showParticleSystems":true,"showVisualEffectGraphs":true,"m_FxEnabled":true},"in2DMode":false,"pivot":{"x":17.59274673461914,"y":-54.32231903076172,"z":57.59107971191406},"rotation":{"x":0.35835975408554079,"y":0.1601790189743042,"z":-0.06254349648952484,"w":0.9176376461982727},"size":73.68927764892578,"orthographic":false}